makemedicom.py
makemedicom-0.0.8.dist-info/METADATA
makemedicom-0.0.8.dist-info/WHEEL
makemedicom-0.0.8.dist-info/entry_points.txt
makemedicom-0.0.8.dist-info/top_level.txt
makemedicom-0.0.8.dist-info/RECORD
