Metadata-Version: 2.1
Name: makemedicom
Version: 0.0.8
Requires-Dist: numpy ==1.*
Requires-Dist: pydicom ==2.4.2
Requires-Dist: h5py ==3.9.0
Requires-Dist: tifffile
